paystacklib/__init__.py
paystacklib/bank.py
paystacklib/baseapi.py
paystacklib/bulkcharge.py
paystacklib/charge.py
paystacklib/customer.py
paystacklib/dictwrapper.py
paystacklib/invoice.py
paystacklib/page.py
paystacklib/paymentsessiontimeout.py
paystacklib/plan.py
paystacklib/product.py
paystacklib/refund.py
paystacklib/settlement.py
paystacklib/subaccount.py
paystacklib/subscription.py
paystacklib/transaction.py
paystacklib/transfer.py
paystacklib/transferrecipient.py
paystacklib/utils.py
paystacklib/verification.py
tests/__init__.py
tests/test.py
paystacklib-0.1.0.dist-info/LICENSE
paystacklib-0.1.0.dist-info/METADATA
paystacklib-0.1.0.dist-info/WHEEL
paystacklib-0.1.0.dist-info/top_level.txt
paystacklib-0.1.0.dist-info/RECORD
