Metadata-Version: 2.1
Name: paystacklib
Version: 0.1.0
Summary: A Python implementation of the Paystack API
Home-page: https://github.com/abimbola/paystack-lib-python
Author: Abimbola Adegun
Author-email: abimbola.adegun@gmail.com
License: UNKNOWN
Platform: UNKNOWN
Classifier: Programming Language :: Python :: 3
Classifier: License :: OSI Approved :: MIT License
Requires-Dist: requests
Requires-Dist: dotmap (>=1.3.8)
